JavaMianshiBiwenJvmKaodianJingjiang/README.md
JavaMianshiBiwenJvmKaodianJingjiang/__init__.py
JavaMianshiBiwenJvmKaodianJingjiang/__main__.py
JavaMianshiBiwenJvmKaodianJingjiang/file.epub
JavaMianshiBiwenJvmKaodianJingjiang/index.html
JavaMianshiBiwenJvmKaodianJingjiang/css/__init__.py
JavaMianshiBiwenJvmKaodianJingjiang/css/annotations.css
JavaMianshiBiwenJvmKaodianJingjiang/css/main.css
JavaMianshiBiwenJvmKaodianJingjiang/css/normalize.css
JavaMianshiBiwenJvmKaodianJingjiang/css/popup.css
JavaMianshiBiwenJvmKaodianJingjiang/font/__init__.py
JavaMianshiBiwenJvmKaodianJingjiang/font/fontello.eot
JavaMianshiBiwenJvmKaodianJingjiang/font/fontello.svg
JavaMianshiBiwenJvmKaodianJingjiang/font/fontello.ttf
JavaMianshiBiwenJvmKaodianJingjiang/font/fontello.woff
JavaMianshiBiwenJvmKaodianJingjiang/img/__init__.py
JavaMianshiBiwenJvmKaodianJingjiang/img/annotator-glyph-sprite.png
JavaMianshiBiwenJvmKaodianJingjiang/img/annotator-icon-sprite.png
JavaMianshiBiwenJvmKaodianJingjiang/img/apple-touch-icon.png
JavaMianshiBiwenJvmKaodianJingjiang/img/cancelfullscreen.png
JavaMianshiBiwenJvmKaodianJingjiang/img/close.png
JavaMianshiBiwenJvmKaodianJingjiang/img/fullscreen.png
JavaMianshiBiwenJvmKaodianJingjiang/img/loader.gif
JavaMianshiBiwenJvmKaodianJingjiang/img/menu-icon.png
JavaMianshiBiwenJvmKaodianJingjiang/img/save.png
JavaMianshiBiwenJvmKaodianJingjiang/img/saved.png
JavaMianshiBiwenJvmKaodianJingjiang/img/settings-s.png
JavaMianshiBiwenJvmKaodianJingjiang/img/settings.png
JavaMianshiBiwenJvmKaodianJingjiang/img/star.png
JavaMianshiBiwenJvmKaodianJingjiang/js/__init__.py
JavaMianshiBiwenJvmKaodianJingjiang/js/epub.js
JavaMianshiBiwenJvmKaodianJingjiang/js/epub.min.js
JavaMianshiBiwenJvmKaodianJingjiang/js/epub.min.map
JavaMianshiBiwenJvmKaodianJingjiang/js/hooks.min.js
JavaMianshiBiwenJvmKaodianJingjiang/js/hooks.min.map
JavaMianshiBiwenJvmKaodianJingjiang/js/reader.js
JavaMianshiBiwenJvmKaodianJingjiang/js/reader.js.map
JavaMianshiBiwenJvmKaodianJingjiang/js/reader.min.js
java_mianshi_biwen_jvm_kaodian_jingjiang-2024.3.5.0.dist-info/METADATA
java_mianshi_biwen_jvm_kaodian_jingjiang-2024.3.5.0.dist-info/WHEEL
java_mianshi_biwen_jvm_kaodian_jingjiang-2024.3.5.0.dist-info/entry_points.txt
java_mianshi_biwen_jvm_kaodian_jingjiang-2024.3.5.0.dist-info/top_level.txt
java_mianshi_biwen_jvm_kaodian_jingjiang-2024.3.5.0.dist-info/RECORD
